orbydev/__init__.py
orbydev/cli.py
orbydev/master.py
orbydev/project.py
orbydev/templates.py
orbydev/templates/default/main.py
orbydev/templates/default/manifest.json
orby_devtools-25.5.2.dist-info/METADATA
orby_devtools-25.5.2.dist-info/WHEEL
orby_devtools-25.5.2.dist-info/entry_points.txt
orby_devtools-25.5.2.dist-info/top_level.txt
orby_devtools-25.5.2.dist-info/RECORD
