Metadata-Version: 2.4
Name: orby-devtools
Version: 25.5.2
Summary: Tools for Orby applications development.
Author-email: Wladisslaw Glebov <your@email.com>
License: MIT
Project-URL: Homepage, https://github.com/wladisslaw/orby-devtools
Classifier: Development Status :: 3 - Alpha
Classifier: Intended Audience :: Developers
Classifier: Programming Language :: Python :: 3.10
Requires-Python: >=3.10
Requires-Dist: click>=8.0
Requires-Dist: pipreqs>=0.4.0
